babelscan/__init__.py
babelscan/__settings__.py
babelscan/babelscan.py
babelscan/csv.py
babelscan/dat.py
babelscan/fitting.py
babelscan/folder_monitor.py
babelscan/functions.py
babelscan/hdf.py
babelscan/instrument.py
babelscan/plotting_matplotlib.py
babelscan/settings.py
babelscan/volume.py
babelscan-0.5.2.dist-info/LICENSE
babelscan-0.5.2.dist-info/METADATA
babelscan-0.5.2.dist-info/WHEEL
babelscan-0.5.2.dist-info/top_level.txt
babelscan-0.5.2.dist-info/RECORD
