Metadata-Version: 2.1
Name: babelscan
Version: 0.5.2
Summary: BabelScan is a format independent data structure for holding different types of data from a scan file
Home-page: https://github.com/DanPorter/babelscan
Author: dgporter
Author-email: dan.porter@diamond.ac.uk
License: Apache 2.0
Keywords: nexus,nexusformat,hdf,scan,data,crystal,diffraction,crystallography,science,x-ray,neutron
Platform: UNKNOWN
Classifier: Programming Language :: Python :: 2.7
Classifier: Programming Language :: Python :: 3.7
Classifier: Intended Audience :: Science/Research
Classifier: Topic :: Scientific/Engineering :: Physics
Classifier: Development Status :: 3 - Alpha
License-File: LICENSE
Requires-Dist: numpy
Requires-Dist: h5py
Requires-Dist: imageio
